README.md
setup.py
cologer/__init__.py
cologer/field.py
cologer/level.py
cologer/lib.py
cologer/main.py
cologer.egg-info/PKG-INFO
cologer.egg-info/SOURCES.txt
cologer.egg-info/dependency_links.txt
cologer.egg-info/requires.txt
cologer.egg-info/top_level.txt